chatgpt_mcp/__init__.py
chatgpt_mcp/chatgpt_automation.py
chatgpt_mcp/chatgpt_mcp.py
chatgpt_mcp/mcp_tools.py
chatgpt_mcp/read_chatgpt_screen.applescript
chatgpt_mcp-1.1.1.dist-info/METADATA
chatgpt_mcp-1.1.1.dist-info/WHEEL
chatgpt_mcp-1.1.1.dist-info/entry_points.txt
chatgpt_mcp-1.1.1.dist-info/licenses/LICENSE
chatgpt_mcp-1.1.1.dist-info/RECORD
