Metadata-Version: 2.4
Name: chatgpt-mcp
Version: 1.1.1
Summary: A Model Context Protocol server for interacting with ChatGPT on macOS with Korean support
Project-URL: Homepage, https://github.com/xncbf/chatgpt-mcp
Project-URL: Repository, https://github.com/xncbf/chatgpt-mcp
Project-URL: Issues, https://github.com/xncbf/chatgpt-mcp/issues
Author-email: Joon Hwan 김준환 <xncbf12@gmail.com>
License: MIT
License-File: LICENSE
Keywords: ai,assistant,automation,chatgpt,macos,mcp
Classifier: Development Status :: 4 - Beta
Classifier: Intended Audience :: Developers
Classifier: License :: OSI Approved :: MIT License
Classifier: Operating System :: MacOS
Classifier: Programming Language :: Python :: 3
Classifier: Programming Language :: Python :: 3.10
Classifier: Programming Language :: Python :: 3.11
Classifier: Programming Language :: Python :: 3.12
Classifier: Topic :: Software Development :: Libraries :: Python Modules
Requires-Python: >=3.10
Requires-Dist: mcp>=1.0.0
Requires-Dist: pyautogui>=0.9.54
